{"i":"1240","c":"SOL030EKS","n":"SOL030EKS","y":[2017,2016,2015,2014,2013,2012,2011,2010],"d":[{"y":2017,"g":"A","c":0},{"y":2017,"g":"B","c":3},{"y":2017,"g":"C","c":5},{"y":2017,"g":"E","c":0},{"y":2016,"g":"A","c":3},{"y":2016,"g":"B","c":12},{"y":2016,"g":"C","c":21},{"y":2016,"g":"D","c":5},{"y":2016,"g":"F","c":0},{"y":2015,"g":"A","c":28},{"y":2015,"g":"B","c":131},{"y":2015,"g":"C","c":117},{"y":2015,"g":"D","c":29},{"y":2015,"g":"E","c":7},{"y":2015,"g":"F","c":0},{"y":2014,"g":"A","c":26},{"y":2014,"g":"B","c":155},{"y":2014,"g":"C","c":134},{"y":2014,"g":"D","c":21},{"y":2014,"g":"E","c":0},{"y":2014,"g":"F","c":0},{"y":2013,"g":"A","c":27},{"y":2013,"g":"B","c":169},{"y":2013,"g":"C","c":123},{"y":2013,"g":"D","c":40},{"y":2013,"g":"E","c":5},{"y":2013,"g":"F","c":0},{"y":2012,"g":"A","c":25},{"y":2012,"g":"B","c":183},{"y":2012,"g":"C","c":139},{"y":2012,"g":"D","c":26},{"y":2012,"g":"E","c":0},{"y":2012,"g":"F","c":3},{"y":2011,"g":"A","c":13},{"y":2011,"g":"B","c":173},{"y":2011,"g":"C","c":138},{"y":2011,"g":"D","c":22},{"y":2011,"g":"E","c":4},{"y":2011,"g":"F","c":0},{"y":2010,"g":"A","c":25},{"y":2010,"g":"B","c":109},{"y":2010,"g":"C","c":134},{"y":2010,"g":"D","c":37},{"y":2010,"g":"E","c":8},{"y":2010,"g":"F","c":0}],"f":"2025-11-25T21:21:07.463Z"}