{"i":"1130","c":"BED-1013","n":"BED-1013","y":[2017,2016,2015,2014],"d":[{"y":2017,"g":"A","c":6},{"y":2017,"g":"B","c":3},{"y":2017,"g":"C","c":6},{"y":2017,"g":"D","c":15},{"y":2017,"g":"E","c":7},{"y":2017,"g":"F","c":18},{"y":2016,"g":"A","c":83},{"y":2016,"g":"B","c":57},{"y":2016,"g":"C","c":53},{"y":2016,"g":"D","c":43},{"y":2016,"g":"E","c":53},{"y":2016,"g":"F","c":91},{"y":2015,"g":"A","c":30},{"y":2015,"g":"B","c":40},{"y":2015,"g":"C","c":39},{"y":2015,"g":"D","c":31},{"y":2015,"g":"E","c":29},{"y":2015,"g":"F","c":54},{"y":2014,"g":"A","c":66},{"y":2014,"g":"B","c":63},{"y":2014,"g":"C","c":45},{"y":2014,"g":"D","c":19},{"y":2014,"g":"E","c":16},{"y":2014,"g":"F","c":37}],"f":"2025-11-25T21:50:49.585Z"}