{"i":"1171","c":"BE-315","n":"BE-315","y":[2017,2016,2015],"d":[{"y":2017,"g":"C","c":0},{"y":2017,"g":"D","c":3},{"y":2017,"g":"E","c":3},{"y":2017,"g":"F","c":0},{"y":2016,"g":"A","c":5},{"y":2016,"g":"B","c":25},{"y":2016,"g":"C","c":16},{"y":2016,"g":"D","c":10},{"y":2016,"g":"E","c":9},{"y":2016,"g":"F","c":10},{"y":2015,"g":"A","c":0},{"y":2015,"g":"B","c":12},{"y":2015,"g":"C","c":20},{"y":2015,"g":"D","c":15},{"y":2015,"g":"E","c":12},{"y":2015,"g":"F","c":14}],"f":"2025-11-25T21:40:10.909Z"}