{"i":"0238","c":"PPU2","n":"PPU2","y":[2020,2019,2018,2017],"d":[{"y":2020,"g":"A","c":19},{"y":2020,"g":"B","c":36},{"y":2020,"g":"C","c":13},{"y":2020,"g":"D","c":0},{"y":2019,"g":"A","c":23},{"y":2019,"g":"B","c":33},{"y":2019,"g":"C","c":18},{"y":2019,"g":"D","c":0},{"y":2019,"g":"F","c":0},{"y":2018,"g":"A","c":43},{"y":2018,"g":"B","c":44},{"y":2018,"g":"C","c":30},{"y":2018,"g":"D","c":0},{"y":2018,"g":"F","c":0},{"y":2017,"g":"A","c":24},{"y":2017,"g":"B","c":28},{"y":2017,"g":"C","c":18},{"y":2017,"g":"D","c":5}],"f":"2025-11-25T22:18:17.932Z"}