{"i":"8241","c":"BØK2302","n":"BØK2302","y":[2013,2012,2011,2010,2009,2008,2007,2006,2005,2004],"d":[{"y":2013,"g":"A","c":4},{"y":2013,"g":"B","c":4},{"y":2013,"g":"C","c":4},{"y":2013,"g":"D","c":0},{"y":2013,"g":"E","c":6},{"y":2013,"g":"F","c":4},{"y":2012,"g":"A","c":15},{"y":2012,"g":"B","c":29},{"y":2012,"g":"C","c":50},{"y":2012,"g":"D","c":28},{"y":2012,"g":"E","c":30},{"y":2012,"g":"F","c":9},{"y":2011,"g":"A","c":31},{"y":2011,"g":"B","c":46},{"y":2011,"g":"C","c":82},{"y":2011,"g":"D","c":60},{"y":2011,"g":"E","c":63},{"y":2011,"g":"F","c":37},{"y":2010,"g":"A","c":55},{"y":2010,"g":"B","c":128},{"y":2010,"g":"C","c":337},{"y":2010,"g":"D","c":296},{"y":2010,"g":"E","c":306},{"y":2010,"g":"F","c":363},{"y":2009,"g":"A","c":73},{"y":2009,"g":"B","c":219},{"y":2009,"g":"C","c":377},{"y":2009,"g":"D","c":308},{"y":2009,"g":"E","c":149},{"y":2009,"g":"F","c":168},{"y":2008,"g":"A","c":40},{"y":2008,"g":"B","c":140},{"y":2008,"g":"C","c":321},{"y":2008,"g":"D","c":262},{"y":2008,"g":"E","c":153},{"y":2008,"g":"F","c":254},{"y":2007,"g":"A","c":21},{"y":2007,"g":"B","c":117},{"y":2007,"g":"C","c":273},{"y":2007,"g":"D","c":21},{"y":2007,"g":"E","c":238},{"y":2007,"g":"F","c":206},{"y":2007,"g":"G","c":0},{"y":2006,"g":"A","c":98},{"y":2006,"g":"B","c":167},{"y":2006,"g":"C","c":250},{"y":2006,"g":"D","c":98},{"y":2006,"g":"E","c":194},{"y":2006,"g":"F","c":178},{"y":2005,"g":"A","c":78},{"y":2005,"g":"B","c":141},{"y":2005,"g":"C","c":223},{"y":2005,"g":"D","c":78},{"y":2005,"g":"E","c":165},{"y":2005,"g":"F","c":104},{"y":2004,"g":"A","c":37},{"y":2004,"g":"B","c":130},{"y":2004,"g":"C","c":234},{"y":2004,"g":"D","c":37},{"y":2004,"g":"E","c":207},{"y":2004,"g":"F","c":190}],"f":"2025-11-25T21:26:53.193Z"}