{"i":"8241","c":"GRA60385","n":"GRA60385","y":[2025,2024,2023],"d":[{"y":2025,"g":"A","c":94},{"y":2025,"g":"B","c":135},{"y":2025,"g":"C","c":75},{"y":2025,"g":"D","c":13},{"y":2025,"g":"E","c":0},{"y":2024,"g":"A","c":119},{"y":2024,"g":"B","c":220},{"y":2024,"g":"C","c":165},{"y":2024,"g":"D","c":30},{"y":2024,"g":"E","c":7},{"y":2024,"g":"F","c":0},{"y":2023,"g":"A","c":54},{"y":2023,"g":"B","c":126},{"y":2023,"g":"C","c":37},{"y":2023,"g":"D","c":4},{"y":2023,"g":"F","c":0}],"f":"2025-11-25T21:28:25.430Z"}